odoo/addons/l10n_fr_chorus_account/README.rst
odoo/addons/l10n_fr_chorus_account/__init__.py
odoo/addons/l10n_fr_chorus_account/__manifest__.py
odoo/addons/l10n_fr_chorus_account/data/ir_cron.xml
odoo/addons/l10n_fr_chorus_account/data/mail_template.xml
odoo/addons/l10n_fr_chorus_account/demo/demo.xml
odoo/addons/l10n_fr_chorus_account/i18n/am.po
odoo/addons/l10n_fr_chorus_account/i18n/bg.po
odoo/addons/l10n_fr_chorus_account/i18n/ca.po
odoo/addons/l10n_fr_chorus_account/i18n/da.po
odoo/addons/l10n_fr_chorus_account/i18n/de.po
odoo/addons/l10n_fr_chorus_account/i18n/el_GR.po
odoo/addons/l10n_fr_chorus_account/i18n/es.po
odoo/addons/l10n_fr_chorus_account/i18n/es_ES.po
odoo/addons/l10n_fr_chorus_account/i18n/es_MX.po
odoo/addons/l10n_fr_chorus_account/i18n/fi.po
odoo/addons/l10n_fr_chorus_account/i18n/fr.po
odoo/addons/l10n_fr_chorus_account/i18n/fr_CH.po
odoo/addons/l10n_fr_chorus_account/i18n/gl.po
odoo/addons/l10n_fr_chorus_account/i18n/hr.po
odoo/addons/l10n_fr_chorus_account/i18n/it.po
odoo/addons/l10n_fr_chorus_account/i18n/l10n_fr_chorus_account.pot
odoo/addons/l10n_fr_chorus_account/i18n/nb_NO.po
odoo/addons/l10n_fr_chorus_account/i18n/nl.po
odoo/addons/l10n_fr_chorus_account/i18n/pt.po
odoo/addons/l10n_fr_chorus_account/i18n/pt_BR.po
odoo/addons/l10n_fr_chorus_account/i18n/pt_PT.po
odoo/addons/l10n_fr_chorus_account/i18n/sl.po
odoo/addons/l10n_fr_chorus_account/i18n/tr.po
odoo/addons/l10n_fr_chorus_account/models/__init__.py
odoo/addons/l10n_fr_chorus_account/models/account_move.py
odoo/addons/l10n_fr_chorus_account/models/chorus_flow.py
odoo/addons/l10n_fr_chorus_account/models/chorus_partner_service.py
odoo/addons/l10n_fr_chorus_account/models/res_company.py
odoo/addons/l10n_fr_chorus_account/models/res_partner.py
odoo/addons/l10n_fr_chorus_account/readme/CONFIGURE.md
odoo/addons/l10n_fr_chorus_account/readme/CONTRIBUTORS.md
odoo/addons/l10n_fr_chorus_account/readme/DESCRIPTION.md
odoo/addons/l10n_fr_chorus_account/readme/USAGE.md
odoo_addon_l10n_fr_chorus_account-18.0.1.0.0.7.dist-info/METADATA
odoo_addon_l10n_fr_chorus_account-18.0.1.0.0.7.dist-info/WHEEL
odoo_addon_l10n_fr_chorus_account-18.0.1.0.0.7.dist-info/top_level.txt
odoo_addon_l10n_fr_chorus_account-18.0.1.0.0.7.dist-info/RECORD
